README.rst
setup.py
simple_tfidf_japanese/__init__.py
simple_tfidf_japanese/tfidf.py
simple_tfidf_japanese.egg-info/PKG-INFO
simple_tfidf_japanese.egg-info/SOURCES.txt
simple_tfidf_japanese.egg-info/dependency_links.txt
simple_tfidf_japanese.egg-info/not-zip-safe
simple_tfidf_japanese.egg-info/requires.txt
simple_tfidf_japanese.egg-info/top_level.txt