Metadata-Version: 1.1
Name: simple-tfidf-japanese
Version: 0.1.3
Summary: Japanese TF-IDF
Home-page: https://github.com/subc/simple_tfidf_japanese
Author: haminiku
Author-email: haminiku1129@gmail.com
License: MIT License
Keywords: tfidf,TF-IDF,Japanese
Platform: UNKNOWN
Classifier: License :: OSI Approved :: MIT License
Classifier: Programming Language :: Python
Classifier: Programming Language :: Python :: 2.6
Classifier: Programming Language :: Python :: 2.7
Classifier: Programming Language :: Python :: 3
Classifier: Programming Language :: Python :: 3.3
Classifier: Programming Language :: Python :: 3.4
